{"file:///Users/valin/Desktop/prufio%20website/prufio":{"assets/images/hashes.json":"+uj7a6ezefxx5Xo+cxv5nQ==","assets/images/pruf-circleu-white-80x80.png":"4wOLbxZCQoLk9PiFTTdVJw==","assets/images/pruf-ap-revised-1836x734.png":"jsu/XnxHUeyBAS5onP9uKg==","assets/images/ipfs-240x240.png":"1I+YJ7Z2Sq2QsCZzy0hggg==","assets/images/arweave-240x66.png":"d5Z+IKDLyPYKppC6vmQckQ==","assets/images/x10-agency-grown-240x240.png":"D+EHuI/Y1DhAWtaKneAj0g==","assets/images/whale-changed-5-240x52.png":"aip7kFb8IdSwcM8hSj/Mjw==","assets/images/entrepreneur-240x240-1-240x240.png":"P+faK5hkuApM7Avq2tbMhA==","assets/images/fxstreet-240x240.png":"D5JlPB3Ftozcu0f6sFer+Q==","assets/images/hackernoon-240x240.png":"fnhs3qbVi9Tmx+s+c203cQ==","assets/images/ibtimes-240x240.png":"H2zkOoeId1bBqv1plEQV+Q==","assets/images/investing-240x240.png":"tGwTOmMvdBku7tei/YNyIg==","assets/images/medium-240x240.png":"HhBEXLL3X80vERulcjlHRg==","assets/images/benzinga-240x240.png":"YzpKotmjFexR/OEIdSvrmw==","assets/images/nulltx-240x240.png":"XE4UIV2qKDhsWLFXUPpinA==","assets/images/publishox-240x240.png":"8xUu8H3EEzzyBJKa1bq8fw==","assets/images/pruf-u-logo-with-border-323x429.png":"/Pc7cnTXSn0KzTCYrE4aQg==","assets/images/tokendistro-1748x989.png":"OXZnby2ZvAzhvxRVzQRxsA==","assets/images/timeline.001-1024x2000.jpg":"GKdtQ3WqBob+YYT79g7w2g==","assets/images/cliff-headshot-506x506.jpg":"IBnZNr2jzdo804FGGlHZ+A==","assets/images/james-headshot-506x506.jpg":"5i7sVyAtO9unT/v6jDO20w==","assets/images/drake-headshot-506x506.jpg":"B4B8dU6kaK3p3SCJ1ZaIxQ==","assets/images/valin-headshot-506x506.jpg":"8VX/iR3jjbLup57zQ8cE3g==","assets/images/sabrina-headshot-506x506.jpg":"zPrpG+/bwTq8XRJKkcluag==","assets/images/raoul-headshot-506x506.jpg":"PH5sq04cHMIowJooMnoycA==","assets/images/adrienne-headshot-506x506.jpg":"AEXhbAbrQO/qMOafGC6mvA==","assets/images/ryan-headshot-506x506.jpg":"10zryZmZkZI5cDGrbFabEg==","assets/images/mbr-1920x1114.jpeg":"6I6EiXKLo1RaJqABZCKhsQ==","assets/images/mbr-1-1920x1114.jpeg":"c42M+N9DzAzfOCVrQ7n/gA==","assets/images/disclaimer-bg-2000x1333.jpg":"tYEx1aKbFsIWP3T559lrnA==","assets/images/info-bg-2000x1500.jpeg":"y6fCbbkfc5ZMMB/XUm/7aA==","assets/images/mbr-1-1920x1080.jpeg":"YUpoxwkUMAp4biA2CuoygQ==","assets/images/mbr-1920x1280.jpg":"KoGWdT8DUdabUMpRsVdQ9g==","assets/images/devs-bg-2000x1333.jpeg":"dE4DWl/ZaeeLpteQQfE3Cg==","assets/web/assets/jquery/jquery.min.js":"3F5/GMjTasHT1HU6h8mNCg==","assets/bootstrap/css/bootstrap.min.css":"gWrw7d07SCLCdWInx+e37g==","assets/bootstrap/css/bootstrap-grid.min.css":"ZpQEaHtj4rsdGDC9wDZdfg==","assets/bootstrap/css/bootstrap-reboot.min.css":"eMZwSLVvZudwLH9xiGj50w==","assets/bootstrap/js/bootstrap.min.js":"AtIjOT4AwnPv3LGt6PT4sQ==","assets/popper/popper.min.js":"NiE4ESlZe/NNSKniYj4FyQ==","assets/tether/tether.min.css":"YhVaOUjL8Xsb9LQHyQq4Tw==","assets/tether/tether.min.js":"PlC291/0Eo8keLHUT4D9+w==","assets/theme/css/style.css":"TToltBSF6Y4a0NZLoX3hQw==","assets/theme/js/script.js":"6hAoWYgSxMaLgaTKKQdxoQ==","assets/smoothscroll/smooth-scroll.js":"e15+ccLIeWb2A3ZYIotPaw==","assets/dropdown/css/style.css":"s+S8lVC62P0BWFtgHpaNFA==","assets/dropdown/js/nav-dropdown.js":"j5pq4WKLRnihd7IVVkQkJg==","assets/dropdown/js/navbar-dropdown.js":"RJXH/341Oa7csvj4pGRDfQ==","assets/touchswipe/jquery.touch-swipe.min.js":"9g/wVGnRdXmW2F9BctT/TQ==","assets/vimeoplayer/jquery.mb.vimeo_player.js":"IfjKT3o1R/fjLMPoouYYzg==","assets/parallax/jarallax.min.js":"rX/x1RkUP0ZMvZZrsxrg7A==","assets/mbr-tabs/mbr-tabs.js":"CdtdEUl+8i34gHIOGPj0cQ==","assets/playervimeo/vimeo_player.js":"IV5sj41WErhIy+BRgYWT7Q==","assets/popup-plugin/script.js":"lwMGKLS/CV2+T7V8ogfGXQ==","assets/popup-ontimer-plugin/script.js":"dToZJzCWDa/N/xVbyYBLQA==","assets/popup-overlay-plugin/script.js":"z83QVk3OeWbUOXnxxooFPg==","assets/web/assets/mobirise-icons2/mobirise2.css":"+RO7OxVtE1FsD/N7V3/ADw==","assets/web/assets/mobirise-icons2/mobirise2.eot":"B2EjryGRojlTpzr1GHt3LQ==","assets/web/assets/mobirise-icons2/mobirise2.svg":"usCYAy7QdzckfeGReb9wWQ==","assets/web/assets/mobirise-icons2/mobirise2.ttf":"VMdAr7YYQ2ab9KiUyabAGA==","assets/web/assets/mobirise-icons2/mobirise2.woff":"xY3InaTfYGp0nlCuQBMudQ==","assets/formstyler/jquery.formstyler.css":"ajjp8ztH9eVUk4rdhVGFYg==","assets/formstyler/jquery.formstyler.js":"Xv5CrVBApokt3elzzhEwuQ==","assets/formstyler/jquery.formstyler.min.js":"AZwL++bNUiLJxmlnInDaEQ==","assets/formstyler/jquery.formstyler.theme.css":"nnzXNu6YBQzXtwPVnmSyMQ==","assets/datepicker/jquery.datetimepicker.min.css":"ho+tif2BPmsXNeoVpuhDPg==","assets/datepicker/jquery.datetimepicker.full.js":"TcRSAGiGustgTlkirRSsRg==","assets/mbr-switch-arrow/mbr-switch-arrow.js":"iI/FHObtma0Hoo0ZPEpQog==","assets/socicon/css/styles.css":"yjHs7tV2SewoW36KZ0bi9w==","assets/socicon/fonts/socicon.eot":"MvYQV8XxgngrhGqjN3oHBw==","assets/socicon/fonts/socicon.svg":"U1iRKoyNjKeR+mUJr3QbXg==","assets/socicon/fonts/socicon.ttf":"IyAo3XNB2a/Q0ml3ZraPsQ==","assets/socicon/fonts/socicon.woff":"zQDjXd6bBUQi87pRsBWVqQ==","assets/socicon/fonts/socicon.woff2":"o3w8h99EHOwP99NXAoHpOQ==","assets/linecons/style.css":"E9DCXxyE91NE7Vyk6eqtOg==","assets/linecons/fonts/linecons.eot":"c+eOjeRrJGMmYN+i0/Bc7g==","assets/linecons/fonts/linecons.svg":"e+dN7itqcS92aCGP2nGUew==","assets/linecons/fonts/linecons.ttf":"iI/EEswIUSoKD7sbT2jq+g==","assets/linecons/fonts/linecons.woff":"ECx3Fs9qAtnElU4n5f59xw==","assets/simple-line-icons/simple-line-icons.css":"Wj4o13c2yaRdVYGBuQ7z6Q==","assets/simple-line-icons/fonts/simple-line-icons.eot":"uR7Hf3WzeerecoItOoEnHg==","assets/simple-line-icons/fonts/simple-line-icons.svg":"L+Lv5jRB2DCxrNEGwf6HNA==","assets/simple-line-icons/fonts/simple-line-icons.ttf":"0UWTju08H9Q1TyHfZZJLFA==","assets/simple-line-icons/fonts/simple-line-icons.woff":"bbJjPKjOqYb1QsVXIavpyQ==","assets/simple-line-icons/fonts/simple-line-icons.woff2":"l919u1+cGZpLkRTbGoEpjA==","assets/web/assets/mobirise-icons/mobirise-icons.css":"t/IrTIzfJvbDUoCV05F+7Q==","assets/web/assets/mobirise-icons/mobirise-icons.eot":"T9iJ+Vffe7n6Gk/+pf9gEw==","assets/web/assets/mobirise-icons/mobirise-icons.svg":"Yp5pSlGdnLgPdQLUa/Yv3w==","assets/web/assets/mobirise-icons/mobirise-icons.ttf":"r0OtN8kuMaYwUc+mlGDUWA==","assets/web/assets/mobirise-icons/mobirise-icons.woff":"3aYYVAIqADvsB1jjxJZ73w==","assets/formoid.min.js":"PCIvx4TB4BdNTxFrmRNOkQ==","assets/recaptcha.css":"rAr6hicA8NHvvo8fHdDrDQ=="}}